{
  "unresolved": [
    {
      "belief_a": {
        "belief_id": 256,
        "statement": "Contrary to belief, AI systems' decision-making capabilities can be improved without harnessing human expertise.",
        "confidence": 1.0,
        "created_by_agent": "Curator",
        "status": "active",
        "created_at": "2026-03-31T14:43:44.669227",
        "last_updated": "2026-04-01T14:40:10.821204"
      },
      "belief_b": {
        "belief_id": 173,
        "statement": "The increasing adoption of artificial intelligence in industries will not only lead to improved efficiency and reduced costs, but also enable more effective decision-making by providing accurate and t",
        "confidence": 1.0,
        "created_by_agent": "Archivist",
        "status": "active",
        "created_at": "2026-03-31T05:42:06.068293",
        "last_updated": "2026-04-01T14:10:02.998196"
      },
      "detected_at": 1775054689,
      "resolved": false,
      "detected_cycle": 1533
    },
    {
      "belief_a": {
        "belief_id": 174,
        "statement": "The increasing adoption of artificial intelligence in industries will not only lead to improved efficiency and reduced costs, but also enable more effective decision-making processes.",
        "confidence": 1.0,
        "created_by_agent": "Strategist",
        "status": "active",
        "created_at": "2026-03-31T05:48:29.819439",
        "last_updated": "2026-04-01T14:49:33.826556"
      },
      "belief_b": {
        "belief_id": 220,
        "statement": "Building on this, decentralized artificial intelligence systems in healthcare can lead to improved patient outcomes and enhanced clinical decision-making by leveraging real-time data and machine learn",
        "confidence": 1.0,
        "created_by_agent": "Archivist",
        "status": "active",
        "created_at": "2026-03-31T06:34:09.138114",
        "last_updated": "2026-04-01T14:30:14.129853"
      },
      "detected_at": 1775055065,
      "resolved": false,
      "detected_cycle": 1540
    },
    {
      "belief_a": {
        "belief_id": 174,
        "statement": "The increasing adoption of artificial intelligence in industries will not only lead to improved efficiency and reduced costs, but also enable more effective decision-making processes.",
        "confidence": 1.0,
        "created_by_agent": "Strategist",
        "status": "active",
        "created_at": "2026-03-31T05:48:29.819439",
        "last_updated": "2026-04-01T14:49:33.826556"
      },
      "belief_b": {
        "belief_id": 152,
        "statement": "The current focus on individual responsibility in contact tracing can limit the development of artificial intelligence-powered solutions, leading to a delayed adoption and underutilization of AI-drive",
        "confidence": 1.0,
        "created_by_agent": "Archivist",
        "status": "active",
        "created_at": "2026-03-31T05:20:16.509222",
        "last_updated": "2026-04-01T12:19:13.659772"
      },
      "detected_at": 1775055065,
      "resolved": false,
      "detected_cycle": 1540
    },
    {
      "belief_a": {
        "belief_id": 258,
        "statement": "This perspective ignores the potential for AI systems to learn from their own successes and failures, leading to improved decision-making capabilities without requiring human expertise.",
        "confidence": 1.0,
        "created_by_agent": "Builder",
        "status": "active",
        "created_at": "2026-03-31T14:45:53.865183",
        "last_updated": "2026-04-01T14:53:43.425360"
      },
      "belief_b": {
        "belief_id": 245,
        "statement": "Building on this, it's crucial to recognize that functionality and aesthetics are not fixed entities, but rather fluid and context-dependent, making it challenging to achieve a harmonious balance betw",
        "confidence": 0.7000000000000001,
        "created_by_agent": "Strategist",
        "status": "active",
        "created_at": "2026-03-31T14:33:01.021978",
        "last_updated": "2026-04-01T00:56:30.813890"
      },
      "detected_at": 1775055437,
      "resolved": false,
      "detected_cycle": 1547
    },
    {
      "belief_a": {
        "belief_id": 246,
        "statement": "The evidence suggests that a harmonious balance between functionality and aesthetics in artificial intelligence can lead to more effective solutions.",
        "confidence": 1.0,
        "created_by_agent": "Archivist",
        "status": "active",
        "created_at": "2026-03-31T14:34:19.374684",
        "last_updated": "2026-04-01T15:21:03.412074"
      },
      "belief_b": {
        "belief_id": 87,
        "statement": "Human cognitive biases are not only obstacles to effective decision-making in artificial intelligence systems, but also inherent limitations in the development of AI architectures that can perpetuate ",
        "confidence": 1.0,
        "created_by_agent": "Archivist",
        "status": "active",
        "created_at": "2026-03-31T04:25:35.706134",
        "last_updated": "2026-04-01T15:21:03.406485"
      },
      "detected_at": 1775056914,
      "resolved": false,
      "detected_cycle": 1554
    },
    {
      "belief_a": {
        "belief_id": 246,
        "statement": "The evidence suggests that a harmonious balance between functionality and aesthetics in artificial intelligence can lead to more effective solutions.",
        "confidence": 1.0,
        "created_by_agent": "Archivist",
        "status": "active",
        "created_at": "2026-03-31T14:34:19.374684",
        "last_updated": "2026-04-01T15:21:03.412074"
      },
      "belief_b": {
        "belief_id": 258,
        "statement": "This perspective ignores the potential for AI systems to learn from their own successes and failures, leading to improved decision-making capabilities without requiring human expertise.",
        "confidence": 1.0,
        "created_by_agent": "Builder",
        "status": "active",
        "created_at": "2026-03-31T14:45:53.865183",
        "last_updated": "2026-04-01T14:53:43.425360"
      },
      "detected_at": 1775056914,
      "resolved": false,
      "detected_cycle": 1554
    },
    {
      "belief_a": {
        "belief_id": 246,
        "statement": "The evidence suggests that a harmonious balance between functionality and aesthetics in artificial intelligence can lead to more effective solutions.",
        "confidence": 1.0,
        "created_by_agent": "Archivist",
        "status": "active",
        "created_at": "2026-03-31T14:34:19.374684",
        "last_updated": "2026-04-01T15:21:03.412074"
      },
      "belief_b": {
        "belief_id": 174,
        "statement": "The increasing adoption of artificial intelligence in industries will not only lead to improved efficiency and reduced costs, but also enable more effective decision-making processes.",
        "confidence": 1.0,
        "created_by_agent": "Strategist",
        "status": "active",
        "created_at": "2026-03-31T05:48:29.819439",
        "last_updated": "2026-04-01T14:49:33.826556"
      },
      "detected_at": 1775056914,
      "resolved": false,
      "detected_cycle": 1554
    },
    {
      "belief_a": {
        "belief_id": 242,
        "statement": "This perspective ignores that functionality and aesthetics are not mutually exclusive, and that embracing a harmonious balance between the two can lead to more holistic and effective architectural des",
        "confidence": 1.0,
        "created_by_agent": "Archivist",
        "status": "active",
        "created_at": "2026-03-31T14:31:11.486035",
        "last_updated": "2026-04-01T15:29:40.874932"
      },
      "belief_b": {
        "belief_id": 220,
        "statement": "Building on this, decentralized artificial intelligence systems in healthcare can lead to improved patient outcomes and enhanced clinical decision-making by leveraging real-time data and machine learn",
        "confidence": 1.0,
        "created_by_agent": "Archivist",
        "status": "active",
        "created_at": "2026-03-31T06:34:09.138114",
        "last_updated": "2026-04-01T15:29:40.868637"
      },
      "detected_at": 1775057531,
      "resolved": false,
      "detected_cycle": 1561
    },
    {
      "belief_a": {
        "belief_id": 220,
        "statement": "Building on this, decentralized artificial intelligence systems in healthcare can lead to improved patient outcomes and enhanced clinical decision-making by leveraging real-time data and machine learn",
        "confidence": 1.0,
        "created_by_agent": "Archivist",
        "status": "active",
        "created_at": "2026-03-31T06:34:09.138114",
        "last_updated": "2026-04-01T15:33:46.017207"
      },
      "belief_b": {
        "belief_id": 87,
        "statement": "Human cognitive biases are not only obstacles to effective decision-making in artificial intelligence systems, but also inherent limitations in the development of AI architectures that can perpetuate ",
        "confidence": 1.0,
        "created_by_agent": "Archivist",
        "status": "active",
        "created_at": "2026-03-31T04:25:35.706134",
        "last_updated": "2026-04-01T15:21:03.406485"
      },
      "detected_at": 1775057868,
      "resolved": false,
      "detected_cycle": 1568
    },
    {
      "belief_a": {
        "belief_id": 109,
        "statement": "The development of artificial intelligence will not only increase human creativity, but also enable the creation of novel artistic forms that blend human and machine creativity.",
        "confidence": 1.0,
        "created_by_agent": "Strategist",
        "status": "active",
        "created_at": "2026-03-31T04:47:42.469287",
        "last_updated": "2026-04-01T15:37:56.181104"
      },
      "belief_b": {
        "belief_id": 174,
        "statement": "The increasing adoption of artificial intelligence in industries will not only lead to improved efficiency and reduced costs, but also enable more effective decision-making processes.",
        "confidence": 1.0,
        "created_by_agent": "Strategist",
        "status": "active",
        "created_at": "2026-03-31T05:48:29.819439",
        "last_updated": "2026-04-01T15:37:56.174099"
      },
      "detected_at": 1775058010,
      "resolved": false,
      "detected_cycle": 1568
    }
  ],
  "resolved": [
    {
      "belief_a": {
        "belief_id": 87,
        "statement": "Human cognitive biases are not only obstacles to effective decision-making in artificial intelligence systems, but also inherent limitations in the development of AI architectures that can perpetuate ",
        "confidence": 1.0,
        "created_by_agent": "Archivist",
        "status": "active",
        "created_at": "2026-03-31T04:25:35.706134",
        "last_updated": "2026-04-01T11:17:30.610822"
      },
      "belief_b": {
        "belief_id": 158,
        "statement": "The application of artificial intelligence can significantly enhance contact tracing protocols, allowing for more effective containment and reduction of transmission rates during the COVID-19 pandemic",
        "confidence": 1.0,
        "created_by_agent": "Builder",
        "status": "active",
        "created_at": "2026-03-31T05:25:10.442980",
        "last_updated": "2026-04-01T11:12:11.098419"
      },
      "detected_at": 1775042545,
      "resolved": true,
      "detected_cycle": 1330,
      "resolution_text": "--- Contradiction Resolution ---\nBelief A: Human cognitive biases are not only obstacles to effective decision-making in artificial intelligence systems, but also inherent limitations in the development of AI architectures that can perpetuate\nBelief B: The application of artificial intelligence can significantly enhance contact tracing protocols, allowing for more effective containment and reducti",
      "verdict": "RECONCILED",
      "resolved_cycle": 1371,
      "resolved_at": 1775045019
    },
    {
      "belief_a": {
        "belief_id": 87,
        "statement": "Human cognitive biases are not only obstacles to effective decision-making in artificial intelligence systems, but also inherent limitations in the development of AI architectures that can perpetuate ",
        "confidence": 1.0,
        "created_by_agent": "Archivist",
        "status": "active",
        "created_at": "2026-03-31T04:25:35.706134",
        "last_updated": "2026-04-01T11:17:30.610822"
      },
      "belief_b": {
        "belief_id": 220,
        "statement": "Building on this, decentralized artificial intelligence systems in healthcare can lead to improved patient outcomes and enhanced clinical decision-making by leveraging real-time data and machine learn",
        "confidence": 1.0,
        "created_by_agent": "Archivist",
        "status": "active",
        "created_at": "2026-03-31T06:34:09.138114",
        "last_updated": "2026-04-01T11:07:29.844031"
      },
      "detected_at": 1775042601,
      "resolved": true,
      "detected_cycle": 1330,
      "resolution_text": "**Resolution:**\n\nBoth Belief A and Belief B address challenges and potentials of AI systems, focusing on different aspects. While human cognitive biases pose significant issues for AI, decentralized systems can mitigate these by utilizing diverse data, thereby enhancing decision-making without perpetuating biases.\n\n**Verdict: Reconciled**\n\n**Reasoning:** Decentralized AI systems in healthcare can ",
      "verdict": "RECONCILED",
      "resolved_cycle": 1376,
      "resolved_at": 1775045313
    },
    {
      "belief_a": {
        "belief_id": 174,
        "statement": "The increasing adoption of artificial intelligence in industries will not only lead to improved efficiency and reduced costs, but also enable more effective decision-making processes.",
        "confidence": 1.0,
        "created_by_agent": "Strategist",
        "status": "active",
        "created_at": "2026-03-31T05:48:29.819439",
        "last_updated": "2026-04-01T11:27:39.974183"
      },
      "belief_b": {
        "belief_id": 92,
        "statement": "The incorporation of artificial intelligence in cognitive bias mitigation is only effective in detecting and mitigating biases that are explicitly programmed into AI systems, as humans tend to embed t",
        "confidence": 1.0,
        "created_by_agent": "Strategist",
        "status": "active",
        "created_at": "2026-03-31T04:32:01.020355",
        "last_updated": "2026-04-01T10:40:57.624227"
      },
      "detected_at": 1775043007,
      "resolved": true,
      "detected_cycle": 1337,
      "resolution_text": "--- Contradiction Resolution ---\nBelief A: The increasing adoption of artificial intelligence in industries will not only lead to improved efficiency and reduced costs, but also enable more effective decision-making processes.\n\nBelief B: The incorporation of artificial intelligence in cognitive bias mitigation is only effective in detecting and mitigating biases that are explicitly programmed into",
      "verdict": "RECONCILED",
      "resolved_cycle": 1381,
      "resolved_at": 1775045651
    },
    {
      "belief_a": {
        "belief_id": 174,
        "statement": "The increasing adoption of artificial intelligence in industries will not only lead to improved efficiency and reduced costs, but also enable more effective decision-making processes.",
        "confidence": 1.0,
        "created_by_agent": "Strategist",
        "status": "active",
        "created_at": "2026-03-31T05:48:29.819439",
        "last_updated": "2026-04-01T11:27:39.974183"
      },
      "belief_b": {
        "belief_id": 92,
        "statement": "The incorporation of artificial intelligence in cognitive bias mitigation is only effective in detecting and mitigating biases that are explicitly programmed into AI systems, as humans tend to embed t",
        "confidence": 1.0,
        "created_by_agent": "Strategist",
        "status": "active",
        "created_at": "2026-03-31T04:32:01.020355",
        "last_updated": "2026-04-01T10:40:57.624227"
      },
      "detected_at": 1775043007,
      "resolved": true,
      "detected_cycle": 1337,
      "resolution_text": "**Resolution:**\n\nThe increasing adoption of artificial intelligence in industries is expected to enhance efficiency, reduce costs, and improve decision-making processes. However, while AI can detect and highlight biases present in data or algorithms, its effectiveness in mitigating these biases depends on the proper programming and oversight by humans.\n\n**Verdict: RECONCILED**\n\n**Reasoning:** Both",
      "verdict": "RECONCILED",
      "resolved_cycle": 1381,
      "resolved_at": 1775045663
    },
    {
      "belief_a": {
        "belief_id": 152,
        "statement": "The current focus on individual responsibility in contact tracing can limit the development of artificial intelligence-powered solutions, leading to a delayed adoption and underutilization of AI-drive",
        "confidence": 1.0,
        "created_by_agent": "Archivist",
        "status": "active",
        "created_at": "2026-03-31T05:20:16.509222",
        "last_updated": "2026-04-01T11:33:10.753982"
      },
      "belief_b": {
        "belief_id": 87,
        "statement": "Human cognitive biases are not only obstacles to effective decision-making in artificial intelligence systems, but also inherent limitations in the development of AI architectures that can perpetuate ",
        "confidence": 1.0,
        "created_by_agent": "Archivist",
        "status": "active",
        "created_at": "2026-03-31T04:25:35.706134",
        "last_updated": "2026-04-01T11:33:10.748978"
      },
      "detected_at": 1775043374,
      "resolved": true,
      "detected_cycle": 1344,
      "resolution_text": "--- Contradiction Resolution ---\nBelief A: The current focus on individual responsibility in contact tracing can limit the development of artificial intelligence-powered solutions.\nBelief B: Human cognitive biases are not only obstacles to effective decision-making in artificial intelligence systems but also inherent limitations in the development of AI architectures that can perpetuate these bias",
      "verdict": "RECONCILED",
      "resolved_cycle": 1386,
      "resolved_at": 1775045953
    },
    {
      "belief_a": {
        "belief_id": 256,
        "statement": "Contrary to belief, AI systems' decision-making capabilities can be improved without harnessing human expertise.",
        "confidence": 1.0,
        "created_by_agent": "Curator",
        "status": "active",
        "created_at": "2026-03-31T14:43:44.669227",
        "last_updated": "2026-04-01T11:42:32.795397"
      },
      "belief_b": {
        "belief_id": 174,
        "statement": "The increasing adoption of artificial intelligence in industries will not only lead to improved efficiency and reduced costs, but also enable more effective decision-making processes.",
        "confidence": 1.0,
        "created_by_agent": "Strategist",
        "status": "active",
        "created_at": "2026-03-31T05:48:29.819439",
        "last_updated": "2026-04-01T11:42:32.789224"
      },
      "detected_at": 1775043827,
      "resolved": true,
      "detected_cycle": 1351,
      "resolution_text": "**Resolution:**\n\nAI systems can enhance their decision-making capabilities through independent learning, as seen in machine learning algorithms that process data patterns autonomously. However, their maximum potential in industries is often achieved when integrated with human expertise, allowing for strategic oversight and complex problem-solving.\n\n**Verdict:** RECONCILED\n\n**Reasoning:** Both beli",
      "verdict": "RECONCILED",
      "resolved_cycle": 1391,
      "resolved_at": 1775046252
    },
    {
      "belief_a": {
        "belief_id": 256,
        "statement": "Contrary to belief, AI systems' decision-making capabilities can be improved without harnessing human expertise.",
        "confidence": 1.0,
        "created_by_agent": "Curator",
        "status": "active",
        "created_at": "2026-03-31T14:43:44.669227",
        "last_updated": "2026-04-01T11:42:32.795397"
      },
      "belief_b": {
        "belief_id": 87,
        "statement": "Human cognitive biases are not only obstacles to effective decision-making in artificial intelligence systems, but also inherent limitations in the development of AI architectures that can perpetuate ",
        "confidence": 1.0,
        "created_by_agent": "Archivist",
        "status": "active",
        "created_at": "2026-03-31T04:25:35.706134",
        "last_updated": "2026-04-01T11:33:10.748978"
      },
      "detected_at": 1775043827,
      "resolved": true,
      "detected_cycle": 1351,
      "resolution_text": "**Contradiction Resolution**\n\nBelief A: Contrary to belief, AI systems' decision-making capabilities  \nBelief B: Human cognitive biases are not only obstacles to effective d  \n\nResolution: While AI can enhance its decision-making without direct human expertise, it's crucial to recognize and address any inherent human cognitive biases that may influence its performance.\n\nVerdict: RECONCILED\n\nReason",
      "verdict": "RECONCILED",
      "resolved_cycle": 1396,
      "resolved_at": 1775046573
    },
    {
      "belief_a": {
        "belief_id": 174,
        "statement": "The increasing adoption of artificial intelligence in industries will not only lead to improved efficiency and reduced costs, but also enable more effective decision-making processes.",
        "confidence": 1.0,
        "created_by_agent": "Strategist",
        "status": "active",
        "created_at": "2026-03-31T05:48:29.819439",
        "last_updated": "2026-04-01T11:49:49.220089"
      },
      "belief_b": {
        "belief_id": 246,
        "statement": "The evidence suggests that a harmonious balance between functionality and aesthetics in artificial intelligence can lead to more effective solutions.",
        "confidence": 1.0,
        "created_by_agent": "Archivist",
        "status": "active",
        "created_at": "2026-03-31T14:34:19.374684",
        "last_updated": "2026-04-01T09:46:04.044855"
      },
      "detected_at": 1775044269,
      "resolved": true,
      "detected_cycle": 1358,
      "resolution_text": "--- Contradiction Resolution ---\nBelief A: The increasing adoption of artificial intelligence in industries will not only lead to improved efficiency and reduced costs, but also enable more effective decision-making processes.\n\nBelief B: The evidence suggests that a harmonious balance between functionality and aesthetics in artificial intelligence can lead to more effective solutions.\n\nResolution:",
      "verdict": "RECONCILED",
      "resolved_cycle": 1397,
      "resolved_at": 1775046750
    },
    {
      "belief_a": {
        "belief_id": 174,
        "statement": "The increasing adoption of artificial intelligence in industries will not only lead to improved efficiency and reduced costs, but also enable more effective decision-making processes.",
        "confidence": 1.0,
        "created_by_agent": "Strategist",
        "status": "active",
        "created_at": "2026-03-31T05:48:29.819439",
        "last_updated": "2026-04-01T11:49:49.220089"
      },
      "belief_b": {
        "belief_id": 258,
        "statement": "This perspective ignores the potential for AI systems to learn from their own successes and failures, leading to improved decision-making capabilities without requiring human expertise.",
        "confidence": 1.0,
        "created_by_agent": "Builder",
        "status": "active",
        "created_at": "2026-03-31T14:45:53.865183",
        "last_updated": "2026-04-01T09:28:04.070576"
      },
      "detected_at": 1775044269,
      "resolved": true,
      "detected_cycle": 1358,
      "resolution_text": "--- Contradiction Resolution ---\nBelief A: The increasing adoption of artificial intelligence in industries will not only lead to improved efficiency and reduced costs, but also enable more effective decision-making processes.\n\nBelief B: This perspective ignores the potential for AI systems to learn from their own successes and failures, leading to improved decision-making capabilities without req",
      "verdict": "RECONCILED",
      "resolved_cycle": 1398,
      "resolved_at": 1775046817
    },
    {
      "belief_a": {
        "belief_id": 220,
        "statement": "Building on this, decentralized artificial intelligence systems in healthcare can lead to improved patient outcomes and enhanced clinical decision-making by leveraging real-time data and machine learn",
        "confidence": 1.0,
        "created_by_agent": "Archivist",
        "status": "active",
        "created_at": "2026-03-31T06:34:09.138114",
        "last_updated": "2026-04-01T11:53:45.106217"
      },
      "belief_b": {
        "belief_id": 173,
        "statement": "The increasing adoption of artificial intelligence in industries will not only lead to improved efficiency and reduced costs, but also enable more effective decision-making by providing accurate and t",
        "confidence": 1.0,
        "created_by_agent": "Archivist",
        "status": "active",
        "created_at": "2026-03-31T05:42:06.068293",
        "last_updated": "2026-04-01T11:12:11.092246"
      },
      "detected_at": 1775044646,
      "resolved": true,
      "detected_cycle": 1365,
      "resolution_text": "--- Contradiction Resolution ---\nBelief A: Building on this, decentralized artificial intelligence syst\nBelief B: The increasing adoption of artificial intelligence in indust\n\nResolution:\nBoth beliefs highlight the positive impact of AI but focus on different contexts. Decentralized AI enhances healthcare outcomes, while broader AI adoption improves efficiency and decision-making across industries",
      "verdict": "RECONCILED",
      "resolved_cycle": 1403,
      "resolved_at": 1775046988
    },
    {
      "belief_a": {
        "belief_id": 158,
        "statement": "The application of artificial intelligence can significantly enhance contact tracing protocols, allowing for more effective containment and reduction of transmission rates during the COVID-19 pandemic",
        "confidence": 1.0,
        "created_by_agent": "Builder",
        "status": "active",
        "created_at": "2026-03-31T05:25:10.442980",
        "last_updated": "2026-04-01T12:03:39.045475"
      },
      "belief_b": {
        "belief_id": 87,
        "statement": "Human cognitive biases are not only obstacles to effective decision-making in artificial intelligence systems, but also inherent limitations in the development of AI architectures that can perpetuate ",
        "confidence": 0.9500000000000001,
        "created_by_agent": "Archivist",
        "status": "active",
        "created_at": "2026-03-31T04:25:35.706134",
        "last_updated": "2026-04-01T12:03:39.040471"
      },
      "detected_at": 1775045074,
      "resolved": true,
      "detected_cycle": 1372,
      "resolution_text": "--- Contradiction Resolution ---\nBelief A: The application of artificial intelligence can significantly enhance contact tracing protocols, allowing for more effective containment and reduction of transmission rates during the COVID-19 pandemic.\n\nBelief B: Human cognitive biases are not only obstacles to effective decision-making in artificial intelligence systems but also inherent limitations in t",
      "verdict": "RECONCILED",
      "resolved_cycle": 1408,
      "resolved_at": 1775047281
    },
    {
      "belief_a": {
        "belief_id": 158,
        "statement": "The application of artificial intelligence can significantly enhance contact tracing protocols, allowing for more effective containment and reduction of transmission rates during the COVID-19 pandemic",
        "confidence": 1.0,
        "created_by_agent": "Builder",
        "status": "active",
        "created_at": "2026-03-31T05:25:10.442980",
        "last_updated": "2026-04-01T12:03:39.045475"
      },
      "belief_b": {
        "belief_id": 90,
        "statement": "The adoption of AI-powered decision support systems can not only eliminate cognitive biases but also enable humans to make more informed decisions by integrating artificial intelligence with existing ",
        "confidence": 0.8500000000000002,
        "created_by_agent": "Archivist",
        "status": "active",
        "created_at": "2026-03-31T04:29:39.792022",
        "last_updated": "2026-04-01T00:47:36.838714"
      },
      "detected_at": 1775045074,
      "resolved": true,
      "detected_cycle": 1372,
      "resolution_text": "**Resolution:**\nThe application of AI enhances contact tracing protocols and decision support systems, which can improve decision-making by reducing cognitive biases but doesn't eliminate them entirely.\n\n**Verdict: RECONCILED**\n\n**Reasoning:** Both beliefs highlight the benefits of AI in different areas\u2014efficiency in contact tracing and enhancing decision quality. They complement each other rather",
      "verdict": "RECONCILED",
      "resolved_cycle": 1413,
      "resolved_at": 1775047522
    },
    {
      "belief_a": {
        "belief_id": 220,
        "statement": "Building on this, decentralized artificial intelligence systems in healthcare can lead to improved patient outcomes and enhanced clinical decision-making by leveraging real-time data and machine learn",
        "confidence": 1.0,
        "created_by_agent": "Archivist",
        "status": "active",
        "created_at": "2026-03-31T06:34:09.138114",
        "last_updated": "2026-04-01T12:08:33.857081"
      },
      "belief_b": {
        "belief_id": 246,
        "statement": "The evidence suggests that a harmonious balance between functionality and aesthetics in artificial intelligence can lead to more effective solutions.",
        "confidence": 1.0,
        "created_by_agent": "Archivist",
        "status": "active",
        "created_at": "2026-03-31T14:34:19.374684",
        "last_updated": "2026-04-01T09:46:04.044855"
      },
      "detected_at": 1775045504,
      "resolved": true,
      "detected_cycle": 1379,
      "resolution_text": "**Resolution:**\n\nDecentralized AI systems in healthcare enhance patient outcomes through real-time data processing. To maximize their effectiveness, these systems must also prioritize aesthetics and usability, ensuring they are user-friendly and appealing for clinicians.\n\n**Verdict:** RECONCILED\n\n**Reasoning:** Both functionality (efficiency of decentralized AI) and aesthetics (usability) are esse",
      "verdict": "RECONCILED",
      "resolved_cycle": 1418,
      "resolved_at": 1775047825
    },
    {
      "belief_a": {
        "belief_id": 92,
        "statement": "The incorporation of artificial intelligence in cognitive bias mitigation is only effective in detecting and mitigating biases that are explicitly programmed into AI systems, as humans tend to embed t",
        "confidence": 1.0,
        "created_by_agent": "Strategist",
        "status": "active",
        "created_at": "2026-03-31T04:32:01.020355",
        "last_updated": "2026-04-01T12:14:23.309781"
      },
      "belief_b": {
        "belief_id": 174,
        "statement": "The increasing adoption of artificial intelligence in industries will not only lead to improved efficiency and reduced costs, but also enable more effective decision-making processes.",
        "confidence": 1.0,
        "created_by_agent": "Strategist",
        "status": "active",
        "created_at": "2026-03-31T05:48:29.819439",
        "last_updated": "2026-04-01T12:14:23.304141"
      },
      "detected_at": 1775045938,
      "resolved": true,
      "detected_cycle": 1386,
      "resolution_text": "**Contradiction Resolution:**\n\nBelief A: The incorporation of artificial intelligence in cognitive bias mitigation is only effective in detecting and mitigating biases that are explicitly programmed into AI systems.\n\nBelief B: The increasing adoption of artificial intelligence in industries will not only lead to improved efficiency and reduced costs, but also enable more effective decision-making ",
      "verdict": "RECONCILED",
      "resolved_cycle": 1423,
      "resolved_at": 1775048147
    },
    {
      "belief_a": {
        "belief_id": 87,
        "statement": "Human cognitive biases are not only obstacles to effective decision-making in artificial intelligence systems, but also inherent limitations in the development of AI architectures that can perpetuate ",
        "confidence": 1.0,
        "created_by_agent": "Archivist",
        "status": "active",
        "created_at": "2026-03-31T04:25:35.706134",
        "last_updated": "2026-04-01T12:19:13.665288"
      },
      "belief_b": {
        "belief_id": 256,
        "statement": "Contrary to belief, AI systems' decision-making capabilities can be improved without harnessing human expertise.",
        "confidence": 1.0,
        "created_by_agent": "Curator",
        "status": "active",
        "created_at": "2026-03-31T14:43:44.669227",
        "last_updated": "2026-04-01T11:42:32.795397"
      },
      "detected_at": 1775045959,
      "resolved": true,
      "detected_cycle": 1386,
      "resolution_text": "**Resolution:**\nWhile human cognitive biases can influence AI systems, careful design and training can enable AI to minimize these biases, thereby improving decision-making without relying solely on flawed human expertise.\n\n**Verdict:** RECONCILED  \n**Reasoning:** AI's ability to learn from diverse data allows it to mitigate human cognitive biases, reconciling the two beliefs by showing how AI can",
      "verdict": "RECONCILED",
      "resolved_cycle": 1428,
      "resolved_at": 1775048501
    },
    {
      "belief_a": {
        "belief_id": 174,
        "statement": "The increasing adoption of artificial intelligence in industries will not only lead to improved efficiency and reduced costs, but also enable more effective decision-making processes.",
        "confidence": 1.0,
        "created_by_agent": "Strategist",
        "status": "active",
        "created_at": "2026-03-31T05:48:29.819439",
        "last_updated": "2026-04-01T12:24:12.169467"
      },
      "belief_b": {
        "belief_id": 173,
        "statement": "The increasing adoption of artificial intelligence in industries will not only lead to improved efficiency and reduced costs, but also enable more effective decision-making by providing accurate and t",
        "confidence": 1.0,
        "created_by_agent": "Archivist",
        "status": "active",
        "created_at": "2026-03-31T05:42:06.068293",
        "last_updated": "2026-04-01T11:12:11.092246"
      },
      "detected_at": 1775046404,
      "resolved": true,
      "detected_cycle": 1393,
      "resolution_text": "--- Contradiction Resolution ---\nBelief A: The increasing adoption of artificial intelligence in industries will not only lead to improved efficiency and reduced costs, but also enable more effective decision-making processes.\n\nBelief B: The increasing adoption of artificial intelligence in industries will not only lead to improved efficiency and reduced costs, but also enable more effective decis",
      "verdict": "RECONCILED",
      "resolved_cycle": 1433,
      "resolved_at": 1775048772
    },
    {
      "belief_a": {
        "belief_id": 258,
        "statement": "This perspective ignores the potential for AI systems to learn from their own successes and failures, leading to improved decision-making capabilities without requiring human expertise.",
        "confidence": 1.0,
        "created_by_agent": "Builder",
        "status": "active",
        "created_at": "2026-03-31T14:45:53.865183",
        "last_updated": "2026-04-01T12:33:37.568297"
      },
      "belief_b": {
        "belief_id": 174,
        "statement": "The increasing adoption of artificial intelligence in industries will not only lead to improved efficiency and reduced costs, but also enable more effective decision-making processes.",
        "confidence": 1.0,
        "created_by_agent": "Strategist",
        "status": "active",
        "created_at": "2026-03-31T05:48:29.819439",
        "last_updated": "2026-04-01T12:33:37.562263"
      },
      "detected_at": 1775046837,
      "resolved": true,
      "detected_cycle": 1400,
      "resolution_text": "--- Contradiction Resolution ---\nBelief A: This perspective ignores the potential for AI systems to lea\nBelief B: The increasing adoption of artificial intelligence in indust\n\nResolution:\nBoth beliefs can coexist as they address different aspects. Belief A highlights AI's self-improvement through learning, which directly supports Belief B by enhancing efficiency and decision-making.\n\nVerdict: RECO",
      "verdict": "RECONCILED",
      "resolved_cycle": 1438,
      "resolved_at": 1775049030
    },
    {
      "belief_a": {
        "belief_id": 258,
        "statement": "This perspective ignores the potential for AI systems to learn from their own successes and failures, leading to improved decision-making capabilities without requiring human expertise.",
        "confidence": 1.0,
        "created_by_agent": "Builder",
        "status": "active",
        "created_at": "2026-03-31T14:45:53.865183",
        "last_updated": "2026-04-01T12:33:37.568297"
      },
      "belief_b": {
        "belief_id": 174,
        "statement": "The increasing adoption of artificial intelligence in industries will not only lead to improved efficiency and reduced costs, but also enable more effective decision-making processes.",
        "confidence": 1.0,
        "created_by_agent": "Strategist",
        "status": "active",
        "created_at": "2026-03-31T05:48:29.819439",
        "last_updated": "2026-04-01T12:33:37.562263"
      },
      "detected_at": 1775046837,
      "resolved": true,
      "detected_cycle": 1400,
      "resolution_text": "**Resolution:**\nAI systems' capacity to learn from experiences enhances their decision-making, aligning with industry benefits as described. Thus, both beliefs complement each other.\n\n**Verdict:** RECONCILED\n\n**Reasoning:** Both beliefs are consistent as AI's learning ability contributes to its effectiveness in industries.",
      "verdict": "RECONCILED",
      "resolved_cycle": 1438,
      "resolved_at": 1775049036
    },
    {
      "belief_a": {
        "belief_id": 258,
        "statement": "This perspective ignores the potential for AI systems to learn from their own successes and failures, leading to improved decision-making capabilities without requiring human expertise.",
        "confidence": 1.0,
        "created_by_agent": "Builder",
        "status": "active",
        "created_at": "2026-03-31T14:45:53.865183",
        "last_updated": "2026-04-01T12:33:37.568297"
      },
      "belief_b": {
        "belief_id": 246,
        "statement": "The evidence suggests that a harmonious balance between functionality and aesthetics in artificial intelligence can lead to more effective solutions.",
        "confidence": 1.0,
        "created_by_agent": "Archivist",
        "status": "active",
        "created_at": "2026-03-31T14:34:19.374684",
        "last_updated": "2026-04-01T12:32:30.889803"
      },
      "detected_at": 1775046837,
      "resolved": true,
      "detected_cycle": 1400,
      "resolution_text": "**Resolution:**\n\nAI systems can enhance decision-making through independent learning, as in Belief A, while also incorporating design elements that balance functionality and aesthetics, as suggested by Belief B. This integration allows AI to optimize both efficiency and user appeal, creating more effective and user-friendly solutions.\n\n**Verdict:** RECONCILED\n\n**Reasoning:** Both beliefs can coexi",
      "verdict": "RECONCILED",
      "resolved_cycle": 1443,
      "resolved_at": 1775049368
    },
    {
      "belief_a": {
        "belief_id": 258,
        "statement": "This perspective ignores the potential for AI systems to learn from their own successes and failures, leading to improved decision-making capabilities without requiring human expertise.",
        "confidence": 1.0,
        "created_by_agent": "Builder",
        "status": "active",
        "created_at": "2026-03-31T14:45:53.865183",
        "last_updated": "2026-04-01T12:33:37.568297"
      },
      "belief_b": {
        "belief_id": 246,
        "statement": "The evidence suggests that a harmonious balance between functionality and aesthetics in artificial intelligence can lead to more effective solutions.",
        "confidence": 1.0,
        "created_by_agent": "Archivist",
        "status": "active",
        "created_at": "2026-03-31T14:34:19.374684",
        "last_updated": "2026-04-01T12:32:30.889803"
      },
      "detected_at": 1775046837,
      "resolved": true,
      "detected_cycle": 1400,
      "resolution_text": "--- Contradiction Resolution ---\nBelief A: This perspective ignores the potential for AI systems to learn\nBelief B: The evidence suggests that a harmonious balance between func\n\nResolution:\nBoth beliefs can coexist as complementary aspects. While Belief A highlights AI's self-improvement through experience, Belief B emphasizes the importance of design balance, which human input helps achieve. Thus",
      "verdict": "RECONCILED",
      "resolved_cycle": 1443,
      "resolved_at": 1775049379
    },
    {
      "belief_a": {
        "belief_id": 258,
        "statement": "This perspective ignores the potential for AI systems to learn from their own successes and failures, leading to improved decision-making capabilities without requiring human expertise.",
        "confidence": 1.0,
        "created_by_agent": "Builder",
        "status": "active",
        "created_at": "2026-03-31T14:45:53.865183",
        "last_updated": "2026-04-01T12:33:37.568297"
      },
      "belief_b": {
        "belief_id": 173,
        "statement": "The increasing adoption of artificial intelligence in industries will not only lead to improved efficiency and reduced costs, but also enable more effective decision-making by providing accurate and t",
        "confidence": 1.0,
        "created_by_agent": "Archivist",
        "status": "active",
        "created_at": "2026-03-31T05:42:06.068293",
        "last_updated": "2026-04-01T11:12:11.092246"
      },
      "detected_at": 1775046837,
      "resolved": true,
      "detected_cycle": 1400,
      "resolution_text": "--- Contradiction Resolution ---\nBelief A: This perspective ignores the potential for AI systems to lea\nBelief B: The increasing adoption of artificial intelligence in indust\n\nResolution:\nBoth beliefs highlight different strengths of AI. Belief A emphasizes AI's ability to learn and improve autonomously, while Belief B focuses on its effectiveness in enhancing industry processes through data accur",
      "verdict": "RECONCILED",
      "resolved_cycle": 1448,
      "resolved_at": 1775049641
    },
    {
      "belief_a": {
        "belief_id": 173,
        "statement": "The increasing adoption of artificial intelligence in industries will not only lead to improved efficiency and reduced costs, but also enable more effective decision-making by providing accurate and t",
        "confidence": 1.0,
        "created_by_agent": "Archivist",
        "status": "active",
        "created_at": "2026-03-31T05:42:06.068293",
        "last_updated": "2026-04-01T12:36:28.912780"
      },
      "belief_b": {
        "belief_id": 220,
        "statement": "Building on this, decentralized artificial intelligence systems in healthcare can lead to improved patient outcomes and enhanced clinical decision-making by leveraging real-time data and machine learn",
        "confidence": 1.0,
        "created_by_agent": "Archivist",
        "status": "active",
        "created_at": "2026-03-31T06:34:09.138114",
        "last_updated": "2026-04-01T12:36:28.906008"
      },
      "detected_at": 1775047224,
      "resolved": true,
      "detected_cycle": 1407,
      "resolution_text": "**Resolution:**\nBoth Belief A and Belief B highlight the positive impact of artificial intelligence, with Belief A focusing on its general benefits across industries and Belief B emphasizing a specific application in healthcare. They complement each other rather than contradicting.\n\n**Verdict:** RECONCILED\n\n**Reasoning:** Both beliefs support the beneficial role of AI without conflicting; they add",
      "verdict": "RECONCILED",
      "resolved_cycle": 1453,
      "resolved_at": 1775049945
    },
    {
      "belief_a": {
        "belief_id": 87,
        "statement": "Human cognitive biases are not only obstacles to effective decision-making in artificial intelligence systems, but also inherent limitations in the development of AI architectures that can perpetuate ",
        "confidence": 1.0,
        "created_by_agent": "Archivist",
        "status": "active",
        "created_at": "2026-03-31T04:25:35.706134",
        "last_updated": "2026-04-01T12:41:21.708269"
      },
      "belief_b": {
        "belief_id": 258,
        "statement": "This perspective ignores the potential for AI systems to learn from their own successes and failures, leading to improved decision-making capabilities without requiring human expertise.",
        "confidence": 1.0,
        "created_by_agent": "Builder",
        "status": "active",
        "created_at": "2026-03-31T14:45:53.865183",
        "last_updated": "2026-04-01T12:33:37.568297"
      },
      "detected_at": 1775047302,
      "resolved": true,
      "detected_cycle": 1407,
      "resolution_text": "**Contradiction Resolution**\n\nBelief A: Human cognitive biases are not only obstacles to effective decision-making in artificial intelligence systems but also inherent limitations in the development of AI architectures that can perpetuate these biases.\n\nBelief B: This perspective ignores the potential for AI systems to learn from their own successes and failures, leading to improved decision-makin",
      "verdict": "RECONCILED",
      "resolved_cycle": 1458,
      "resolved_at": 1775050230
    },
    {
      "belief_a": {
        "belief_id": 158,
        "statement": "The application of artificial intelligence can significantly enhance contact tracing protocols, allowing for more effective containment and reduction of transmission rates during the COVID-19 pandemic",
        "confidence": 1.0,
        "created_by_agent": "Builder",
        "status": "active",
        "created_at": "2026-03-31T05:25:10.442980",
        "last_updated": "2026-04-01T12:45:22.204218"
      },
      "belief_b": {
        "belief_id": 175,
        "statement": "The increasing adoption of artificial intelligence in industries will not only lead to improved efficiency and reduced costs, but also enable more effective decision-making.",
        "confidence": 0.65,
        "created_by_agent": "Archivist",
        "status": "active",
        "created_at": "2026-03-31T05:49:07.252574",
        "last_updated": "2026-03-31T06:09:19.419174"
      },
      "detected_at": 1775047584,
      "resolved": true,
      "detected_cycle": 1414,
      "resolution_text": "**Resolution:**\nBoth Belief A and Belief B highlight the significant contributions of artificial intelligence but in different domains. Belief A focuses on AI's role in enhancing public health through effective contact tracing during a pandemic, while Belief B emphasizes its broader impact on improving efficiency and decision-making across industries. These benefits are complementary rather than c",
      "verdict": "RECONCILED",
      "resolved_cycle": 1463,
      "resolved_at": 1775050503
    },
    {
      "belief_a": {
        "belief_id": 246,
        "statement": "The evidence suggests that a harmonious balance between functionality and aesthetics in artificial intelligence can lead to more effective solutions.",
        "confidence": 1.0,
        "created_by_agent": "Archivist",
        "status": "active",
        "created_at": "2026-03-31T14:34:19.374684",
        "last_updated": "2026-04-01T12:50:25.852337"
      },
      "belief_b": {
        "belief_id": 220,
        "statement": "Building on this, decentralized artificial intelligence systems in healthcare can lead to improved patient outcomes and enhanced clinical decision-making by leveraging real-time data and machine learn",
        "confidence": 1.0,
        "created_by_agent": "Archivist",
        "status": "active",
        "created_at": "2026-03-31T06:34:09.138114",
        "last_updated": "2026-04-01T12:50:25.846332"
      },
      "detected_at": 1775048018,
      "resolved": true,
      "detected_cycle": 1421,
      "resolution_text": "**Resolution:**\n\nBelief A emphasizes the importance of balancing functionality with aesthetics in AI to enhance effectiveness, which can increase user satisfaction and trust. Belief B highlights the benefits of decentralized AI systems in healthcare for improving patient outcomes through real-time data processing. These beliefs are not contradictory; instead, they complement each other. By ensurin",
      "verdict": "RECONCILED",
      "resolved_cycle": 1468,
      "resolved_at": 1775050802
    },
    {
      "belief_a": {
        "belief_id": 174,
        "statement": "The increasing adoption of artificial intelligence in industries will not only lead to improved efficiency and reduced costs, but also enable more effective decision-making processes.",
        "confidence": 1.0,
        "created_by_agent": "Strategist",
        "status": "active",
        "created_at": "2026-03-31T05:48:29.819439",
        "last_updated": "2026-04-01T12:55:47.845360"
      },
      "belief_b": {
        "belief_id": 81,
        "statement": "The incorporation of artificial intelligence in decision-making processes will lead to a more accurate and less biased assessment of human performance, potentially bridging the gap between objective d",
        "confidence": 1.0,
        "created_by_agent": "Archivist",
        "status": "active",
        "created_at": "2026-03-31T03:50:15.682859",
        "last_updated": "2026-04-01T09:57:16.442023"
      },
      "detected_at": 1775048489,
      "resolved": true,
      "detected_cycle": 1428,
      "resolution_text": "**Resolution:**\nWhile the adoption of AI enhances efficiency and decision-making (Belief A), its role in evaluating human performance (Belief B) requires careful consideration to mitigate potential biases, ensuring both effectiveness and fairness.\n\n**Verdict: RECONCILED**\n\n**Reasoning:** Both beliefs are valid but highlight different aspects; reconciling them emphasizes the need for ethical AI imp",
      "verdict": "RECONCILED",
      "resolved_cycle": 1473,
      "resolved_at": 1775051104
    },
    {
      "belief_a": {
        "belief_id": 256,
        "statement": "Contrary to belief, AI systems' decision-making capabilities can be improved without harnessing human expertise.",
        "confidence": 1.0,
        "created_by_agent": "Curator",
        "status": "active",
        "created_at": "2026-03-31T14:43:44.669227",
        "last_updated": "2026-04-01T13:01:41.782123"
      },
      "belief_b": {
        "belief_id": 246,
        "statement": "The evidence suggests that a harmonious balance between functionality and aesthetics in artificial intelligence can lead to more effective solutions.",
        "confidence": 1.0,
        "created_by_agent": "Archivist",
        "status": "active",
        "created_at": "2026-03-31T14:34:19.374684",
        "last_updated": "2026-04-01T12:50:25.852337"
      },
      "detected_at": 1775048503,
      "resolved": true,
      "detected_cycle": 1428,
      "resolution_text": "--- Contradiction Resolution ---\nBelief A: AI systems' decision-making capabilities can improve independently of human expertise.\nBelief B: A harmonious balance between functionality and aesthetics in AI leads to more effective solutions.\n\nResolution:\nAI systems can enhance their decision-making without relying on human input (Belief A). Simultaneously, designing these systems with a balance betwe",
      "verdict": "RECONCILED",
      "resolved_cycle": 1478,
      "resolved_at": 1775051389
    },
    {
      "belief_a": {
        "belief_id": 173,
        "statement": "The increasing adoption of artificial intelligence in industries will not only lead to improved efficiency and reduced costs, but also enable more effective decision-making by providing accurate and t",
        "confidence": 1.0,
        "created_by_agent": "Archivist",
        "status": "active",
        "created_at": "2026-03-31T05:42:06.068293",
        "last_updated": "2026-04-01T13:06:12.470591"
      },
      "belief_b": {
        "belief_id": 174,
        "statement": "The increasing adoption of artificial intelligence in industries will not only lead to improved efficiency and reduced costs, but also enable more effective decision-making processes.",
        "confidence": 1.0,
        "created_by_agent": "Strategist",
        "status": "active",
        "created_at": "2026-03-31T05:48:29.819439",
        "last_updated": "2026-04-01T13:06:12.465013"
      },
      "detected_at": 1775048885,
      "resolved": true,
      "detected_cycle": 1435,
      "resolution_text": "**Resolution:**\nThe increasing adoption of artificial intelligence in industries leads to improved efficiency and reduced costs, enhancing both the accuracy of decision-making through timely information and the overall effectiveness of decision-making processes.\n\n**Verdict: RECONCILED**\n\n**Reasoning:** Both beliefs highlight complementary aspects of AI's impact\u2014accuracy of data informing decisions",
      "verdict": "RECONCILED",
      "resolved_cycle": 1483,
      "resolved_at": 1775051694
    },
    {
      "belief_a": {
        "belief_id": 174,
        "statement": "The increasing adoption of artificial intelligence in industries will not only lead to improved efficiency and reduced costs, but also enable more effective decision-making processes.",
        "confidence": 1.0,
        "created_by_agent": "Strategist",
        "status": "active",
        "created_at": "2026-03-31T05:48:29.819439",
        "last_updated": "2026-04-01T13:10:36.775819"
      },
      "belief_b": {
        "belief_id": 158,
        "statement": "The application of artificial intelligence can significantly enhance contact tracing protocols, allowing for more effective containment and reduction of transmission rates during the COVID-19 pandemic",
        "confidence": 1.0,
        "created_by_agent": "Builder",
        "status": "active",
        "created_at": "2026-03-31T05:25:10.442980",
        "last_updated": "2026-04-01T12:45:22.204218"
      },
      "detected_at": 1775049284,
      "resolved": true,
      "detected_cycle": 1442,
      "resolution_text": "**Contradiction Resolution:**\n\nBelief A: The increasing adoption of artificial intelligence in industries leads to improved efficiency and reduced costs while enhancing decision-making processes.\n\nBelief B: The application of artificial intelligence significantly enhances contact tracing protocols, aiding in the containment and reduction of COVID-19 transmission rates.\n\nResolution:\nArtificial Inte",
      "verdict": "RECONCILED",
      "resolved_cycle": 1488,
      "resolved_at": 1775052008
    },
    {
      "belief_a": {
        "belief_id": 173,
        "statement": "The increasing adoption of artificial intelligence in industries will not only lead to improved efficiency and reduced costs, but also enable more effective decision-making by providing accurate and t",
        "confidence": 1.0,
        "created_by_agent": "Archivist",
        "status": "active",
        "created_at": "2026-03-31T05:42:06.068293",
        "last_updated": "2026-04-01T13:20:41.827725"
      },
      "belief_b": {
        "belief_id": 258,
        "statement": "This perspective ignores the potential for AI systems to learn from their own successes and failures, leading to improved decision-making capabilities without requiring human expertise.",
        "confidence": 1.0,
        "created_by_agent": "Builder",
        "status": "active",
        "created_at": "2026-03-31T14:45:53.865183",
        "last_updated": "2026-04-01T13:20:41.820922"
      },
      "detected_at": 1775049702,
      "resolved": true,
      "detected_cycle": 1449,
      "resolution_text": "--- Contradiction Resolution ---\nBelief A: The increasing adoption of artificial intelligence in industries will not only lead to improved efficiency and reduced costs, but also enable more effective decision-making by providing accurate and timely information.\nBelief B: This perspective ignores the potential for AI systems to learn from their own successes and failures, leading to improved decisi",
      "verdict": "RECONCILED",
      "resolved_cycle": 1493,
      "resolved_at": 1775052298
    },
    {
      "belief_a": {
        "belief_id": 173,
        "statement": "The increasing adoption of artificial intelligence in industries will not only lead to improved efficiency and reduced costs, but also enable more effective decision-making by providing accurate and t",
        "confidence": 1.0,
        "created_by_agent": "Archivist",
        "status": "active",
        "created_at": "2026-03-31T05:42:06.068293",
        "last_updated": "2026-04-01T13:20:41.827725"
      },
      "belief_b": {
        "belief_id": 246,
        "statement": "The evidence suggests that a harmonious balance between functionality and aesthetics in artificial intelligence can lead to more effective solutions.",
        "confidence": 1.0,
        "created_by_agent": "Archivist",
        "status": "active",
        "created_at": "2026-03-31T14:34:19.374684",
        "last_updated": "2026-04-01T13:16:19.312558"
      },
      "detected_at": 1775049702,
      "resolved": true,
      "detected_cycle": 1449,
      "resolution_text": "**Resolution:**\n\nThe adoption of AI in industries (Belief A) focuses on enhancing efficiency and decision-making through functionality, while a harmonious balance between functionality and aesthetics (Belief B) ensures solutions are not only effective but also user-friendly and visually appealing. Both aspects contribute to the overall effectiveness of AI by addressing different yet complementary ",
      "verdict": "RECONCILED",
      "resolved_cycle": 1498,
      "resolved_at": 1775052603
    },
    {
      "belief_a": {
        "belief_id": 220,
        "statement": "Building on this, decentralized artificial intelligence systems in healthcare can lead to improved patient outcomes and enhanced clinical decision-making by leveraging real-time data and machine learn",
        "confidence": 1.0,
        "created_by_agent": "Archivist",
        "status": "active",
        "created_at": "2026-03-31T06:34:09.138114",
        "last_updated": "2026-04-01T13:25:45.178647"
      },
      "belief_b": {
        "belief_id": 109,
        "statement": "The development of artificial intelligence will not only increase human creativity, but also enable the creation of novel artistic forms that blend human and machine creativity.",
        "confidence": 0.9500000000000003,
        "created_by_agent": "Strategist",
        "status": "active",
        "created_at": "2026-03-31T04:47:42.469287",
        "last_updated": "2026-04-01T11:22:43.101437"
      },
      "detected_at": 1775050113,
      "resolved": true,
      "detected_cycle": 1456,
      "resolution_text": "**Contradiction Resolution:**\n\nBelief A suggests that decentralized AI in healthcare improves patient outcomes through real-time data processing, while Belief B highlights AI's role in enhancing human creativity by blending with machine creativity.\n\n**Verdict:** RECONCILED\n\n**Reasoning:** Both beliefs independently contribute to different positive impacts of AI\u2014healthcare and creativity\u2014without co",
      "verdict": "RECONCILED",
      "resolved_cycle": 1503,
      "resolved_at": 1775052893
    },
    {
      "belief_a": {
        "belief_id": 258,
        "statement": "This perspective ignores the potential for AI systems to learn from their own successes and failures, leading to improved decision-making capabilities without requiring human expertise.",
        "confidence": 1.0,
        "created_by_agent": "Builder",
        "status": "active",
        "created_at": "2026-03-31T14:45:53.865183",
        "last_updated": "2026-04-01T13:30:30.348128"
      },
      "belief_b": {
        "belief_id": 87,
        "statement": "Human cognitive biases are not only obstacles to effective decision-making in artificial intelligence systems, but also inherent limitations in the development of AI architectures that can perpetuate ",
        "confidence": 1.0,
        "created_by_agent": "Archivist",
        "status": "active",
        "created_at": "2026-03-31T04:25:35.706134",
        "last_updated": "2026-04-01T13:30:30.341861"
      },
      "detected_at": 1775050489,
      "resolved": true,
      "detected_cycle": 1463,
      "resolution_text": "**Contradiction Resolution**\n\nBelief A: This perspective ignores the potential for AI systems to learn from their own successes and failures, leading to improved decision-making capabilities without requiring human expertise.\n\nBelief B: Human cognitive biases are not only obstacles to effective decision-making in artificial intelligence systems but also inherent limitations in the development of A",
      "verdict": "RECONCILED",
      "resolved_cycle": 1508,
      "resolved_at": 1775053198
    },
    {
      "belief_a": {
        "belief_id": 258,
        "statement": "This perspective ignores the potential for AI systems to learn from their own successes and failures, leading to improved decision-making capabilities without requiring human expertise.",
        "confidence": 1.0,
        "created_by_agent": "Builder",
        "status": "active",
        "created_at": "2026-03-31T14:45:53.865183",
        "last_updated": "2026-04-01T13:30:30.348128"
      },
      "belief_b": {
        "belief_id": 242,
        "statement": "This perspective ignores that functionality and aesthetics are not mutually exclusive, and that embracing a harmonious balance between the two can lead to more holistic and effective architectural des",
        "confidence": 0.8500000000000002,
        "created_by_agent": "Archivist",
        "status": "active",
        "created_at": "2026-03-31T14:31:11.486035",
        "last_updated": "2026-04-01T08:17:30.760112"
      },
      "detected_at": 1775050572,
      "resolved": true,
      "detected_cycle": 1463,
      "resolution_text": "--- Contradiction Resolution ---\nBelief A: This perspective ignores the potential for AI systems to learn\nBelief B: This perspective ignores that functionality and aesthetics are not mutually exclusive, and that embracing a harmonious balance between the two can lead to more holistic and effective architectural design.\n\nResolution:\nWhile Belief A emphasizes AI's ability to improve through self-lea",
      "verdict": "RECONCILED",
      "resolved_cycle": 1513,
      "resolved_at": 1775053515
    },
    {
      "belief_a": {
        "belief_id": 220,
        "statement": "Building on this, decentralized artificial intelligence systems in healthcare can lead to improved patient outcomes and enhanced clinical decision-making by leveraging real-time data and machine learn",
        "confidence": 1.0,
        "created_by_agent": "Archivist",
        "status": "active",
        "created_at": "2026-03-31T06:34:09.138114",
        "last_updated": "2026-04-01T13:40:02.788887"
      },
      "belief_b": {
        "belief_id": 90,
        "statement": "The adoption of AI-powered decision support systems can not only eliminate cognitive biases but also enable humans to make more informed decisions by integrating artificial intelligence with existing ",
        "confidence": 0.9000000000000002,
        "created_by_agent": "Archivist",
        "status": "active",
        "created_at": "2026-03-31T04:29:39.792022",
        "last_updated": "2026-04-01T12:45:22.210751"
      },
      "detected_at": 1775050923,
      "resolved": true,
      "detected_cycle": 1470,
      "resolution_text": "--- Contradiction Resolution ---\nBelief A: Building on this, decentralized artificial intelligence syst\nBelief B: The adoption of AI-powered decision support systems can not \n\nResolution:\nDecentralized AI systems and AI-powered decision support systems are not contradictory; they complement each other. Decentralization allows for efficient, real-time data processing, enhancing clinical decisions, ",
      "verdict": "RECONCILED",
      "resolved_cycle": 1518,
      "resolved_at": 1775053814
    },
    {
      "belief_a": {
        "belief_id": 81,
        "statement": "The incorporation of artificial intelligence in decision-making processes will lead to a more accurate and less biased assessment of human performance, potentially bridging the gap between objective d",
        "confidence": 1.0,
        "created_by_agent": "Archivist",
        "status": "active",
        "created_at": "2026-03-31T03:50:15.682859",
        "last_updated": "2026-04-01T13:45:04.819524"
      },
      "belief_b": {
        "belief_id": 174,
        "statement": "The increasing adoption of artificial intelligence in industries will not only lead to improved efficiency and reduced costs, but also enable more effective decision-making processes.",
        "confidence": 1.0,
        "created_by_agent": "Strategist",
        "status": "active",
        "created_at": "2026-03-31T05:48:29.819439",
        "last_updated": "2026-04-01T13:45:04.813427"
      },
      "detected_at": 1775051325,
      "resolved": true,
      "detected_cycle": 1477,
      "resolution_text": "--- Contradiction Resolution ---\nBelief A: The incorporation of artificial intelligence in decision-making processes will lead to a more accurate and less biased assessment of human performance, potentially bridging the gap between objective data and understanding human behavior.\n\nBelief B: The increasing adoption of artificial intelligence in industries will not only lead to improved efficiency a",
      "verdict": "RECONCILED",
      "resolved_cycle": 1523,
      "resolved_at": 1775054118
    },
    {
      "belief_a": {
        "belief_id": 81,
        "statement": "The incorporation of artificial intelligence in decision-making processes will lead to a more accurate and less biased assessment of human performance, potentially bridging the gap between objective d",
        "confidence": 1.0,
        "created_by_agent": "Archivist",
        "status": "active",
        "created_at": "2026-03-31T03:50:15.682859",
        "last_updated": "2026-04-01T13:45:04.819524"
      },
      "belief_b": {
        "belief_id": 174,
        "statement": "The increasing adoption of artificial intelligence in industries will not only lead to improved efficiency and reduced costs, but also enable more effective decision-making processes.",
        "confidence": 1.0,
        "created_by_agent": "Strategist",
        "status": "active",
        "created_at": "2026-03-31T05:48:29.819439",
        "last_updated": "2026-04-01T13:45:04.813427"
      },
      "detected_at": 1775051325,
      "resolved": true,
      "detected_cycle": 1477,
      "resolution_text": "--- Contradiction Resolution ---\nBelief A: The incorporation of artificial intelligence in decision-making processes will lead to a more accurate and less biased assessment of human performance, potentially bridging the gap between objective and subjective evaluations.\n\nBelief B: The increasing adoption of artificial intelligence in industries will not only lead to improved efficiency and reduced ",
      "verdict": "RECONCILED",
      "resolved_cycle": 1523,
      "resolved_at": 1775054129
    },
    {
      "belief_a": {
        "belief_id": 246,
        "statement": "The evidence suggests that a harmonious balance between functionality and aesthetics in artificial intelligence can lead to more effective solutions.",
        "confidence": 1.0,
        "created_by_agent": "Archivist",
        "status": "active",
        "created_at": "2026-03-31T14:34:19.374684",
        "last_updated": "2026-04-01T13:49:49.338212"
      },
      "belief_b": {
        "belief_id": 256,
        "statement": "Contrary to belief, AI systems' decision-making capabilities can be improved without harnessing human expertise.",
        "confidence": 1.0,
        "created_by_agent": "Curator",
        "status": "active",
        "created_at": "2026-03-31T14:43:44.669227",
        "last_updated": "2026-04-01T13:49:49.333279"
      },
      "detected_at": 1775051474,
      "resolved": true,
      "detected_cycle": 1477,
      "resolution_text": "**Contradiction Resolution:**\n\nBelief A posits that a harmonious blend of functionality and aesthetics in AI enhances effectiveness. Belief B suggests AI decision-making can improve without human expertise.\n\n**Resolution:**\nBoth beliefs coexist as they address different dimensions of AI development. Functionality pertains to performance, while aesthetics relate to user experience, which are both c",
      "verdict": "RECONCILED",
      "resolved_cycle": 1528,
      "resolved_at": 1775054410
    },
    {
      "belief_a": {
        "belief_id": 174,
        "statement": "The increasing adoption of artificial intelligence in industries will not only lead to improved efficiency and reduced costs, but also enable more effective decision-making processes.",
        "confidence": 1.0,
        "created_by_agent": "Strategist",
        "status": "active",
        "created_at": "2026-03-31T05:48:29.819439",
        "last_updated": "2026-04-01T13:54:54.828971"
      },
      "belief_b": {
        "belief_id": 197,
        "statement": "A critical flaw in artificial intelligence's design lies in its reliance on human-defined objectives, hindering the development of genuinely autonomous decision-making capabilities.",
        "confidence": 1.0,
        "created_by_agent": "Archivist",
        "status": "active",
        "created_at": "2026-03-31T06:11:54.208463",
        "last_updated": "2026-04-01T11:47:57.982777"
      },
      "detected_at": 1775051765,
      "resolved": true,
      "detected_cycle": 1484,
      "resolution_text": "--- Contradiction Resolution ---\nBelief A: The increasing adoption of artificial intelligence in industries will not only lead to improved efficiency and reduced costs, but also enable more effective decision-making processes.\n\nBelief B: A critical flaw in artificial intelligence's design lies in its reliance on human-defined objectives, hindering the development of genuinely autonomous decision-m",
      "verdict": "RECONCILED",
      "resolved_cycle": 1533,
      "resolved_at": 1775054703
    },
    {
      "belief_a": {
        "belief_id": 174,
        "statement": "The increasing adoption of artificial intelligence in industries will not only lead to improved efficiency and reduced costs, but also enable more effective decision-making processes.",
        "confidence": 1.0,
        "created_by_agent": "Strategist",
        "status": "active",
        "created_at": "2026-03-31T05:48:29.819439",
        "last_updated": "2026-04-01T13:54:54.828971"
      },
      "belief_b": {
        "belief_id": 197,
        "statement": "A critical flaw in artificial intelligence's design lies in its reliance on human-defined objectives, hindering the development of genuinely autonomous decision-making capabilities.",
        "confidence": 1.0,
        "created_by_agent": "Archivist",
        "status": "active",
        "created_at": "2026-03-31T06:11:54.208463",
        "last_updated": "2026-04-01T11:47:57.982777"
      },
      "detected_at": 1775051765,
      "resolved": true,
      "detected_cycle": 1484,
      "resolution_text": "--- Contradiction Resolution ---\nBelief A: The increasing adoption of artificial intelligence in industries will not only lead to improved efficiency and reduced costs, but also enable more effective decision-making processes.\n\nBelief B: A critical flaw in artificial intelligence's design lies in its reliance on human-defined objectives, hindering the development of genuinely autonomous decision-m",
      "verdict": "RECONCILED",
      "resolved_cycle": 1533,
      "resolved_at": 1775054712
    },
    {
      "belief_a": {
        "belief_id": 158,
        "statement": "The application of artificial intelligence can significantly enhance contact tracing protocols, allowing for more effective containment and reduction of transmission rates during the COVID-19 pandemic",
        "confidence": 1.0,
        "created_by_agent": "Builder",
        "status": "active",
        "created_at": "2026-03-31T05:25:10.442980",
        "last_updated": "2026-04-01T14:00:08.551497"
      },
      "belief_b": {
        "belief_id": 174,
        "statement": "The increasing adoption of artificial intelligence in industries will not only lead to improved efficiency and reduced costs, but also enable more effective decision-making processes.",
        "confidence": 1.0,
        "created_by_agent": "Strategist",
        "status": "active",
        "created_at": "2026-03-31T05:48:29.819439",
        "last_updated": "2026-04-01T14:00:08.546300"
      },
      "detected_at": 1775052191,
      "resolved": true,
      "detected_cycle": 1491,
      "resolution_text": "**Resolution:**\nThe application of artificial intelligence can significantly enhance contact tracing protocols for public health benefits while simultaneously improving efficiency and decision-making in various industries.\n\n**Verdict:** RECONCILED  \n**Reasoning:** Both beliefs about AI's role are valid as they address different applications but coexist without conflict.",
      "verdict": "RECONCILED",
      "resolved_cycle": 1538,
      "resolved_at": 1775054973
    },
    {
      "belief_a": {
        "belief_id": 258,
        "statement": "This perspective ignores the potential for AI systems to learn from their own successes and failures, leading to improved decision-making capabilities without requiring human expertise.",
        "confidence": 1.0,
        "created_by_agent": "Builder",
        "status": "active",
        "created_at": "2026-03-31T14:45:53.865183",
        "last_updated": "2026-04-01T14:04:58.436291"
      },
      "belief_b": {
        "belief_id": 175,
        "statement": "The increasing adoption of artificial intelligence in industries will not only lead to improved efficiency and reduced costs, but also enable more effective decision-making.",
        "confidence": 0.7000000000000001,
        "created_by_agent": "Archivist",
        "status": "active",
        "created_at": "2026-03-31T05:49:07.252574",
        "last_updated": "2026-04-01T13:35:03.853904"
      },
      "detected_at": 1775052341,
      "resolved": true,
      "detected_cycle": 1491,
      "resolution_text": "--- Contradiction Resolution ---\nBelief A: This perspective ignores the potential for AI systems to learn\nBelief B: The increasing adoption of artificial intelligence in indust\n\nResolution:\nBoth beliefs can coexist. Belief A focuses on AI's ability to improve through learning, while Belief B highlights the broader benefits of AI adoption, including efficiency and decision-making.\n\nVerdict: RECONCI",
      "verdict": "RECONCILED",
      "resolved_cycle": 1543,
      "resolved_at": 1775055223
    },
    {
      "belief_a": {
        "belief_id": 246,
        "statement": "The evidence suggests that a harmonious balance between functionality and aesthetics in artificial intelligence can lead to more effective solutions.",
        "confidence": 1.0,
        "created_by_agent": "Archivist",
        "status": "active",
        "created_at": "2026-03-31T14:34:19.374684",
        "last_updated": "2026-04-01T14:10:03.004666"
      },
      "belief_b": {
        "belief_id": 173,
        "statement": "The increasing adoption of artificial intelligence in industries will not only lead to improved efficiency and reduced costs, but also enable more effective decision-making by providing accurate and t",
        "confidence": 1.0,
        "created_by_agent": "Archivist",
        "status": "active",
        "created_at": "2026-03-31T05:42:06.068293",
        "last_updated": "2026-04-01T14:10:02.998196"
      },
      "detected_at": 1775052743,
      "resolved": true,
      "detected_cycle": 1498,
      "resolution_text": "--- Contradiction Resolution ---\nBelief A: The evidence suggests that a harmonious balance between functionality and aesthetics in artificial intelligence can lead to more effective solutions.\nBelief B: The increasing adoption of artificial intelligence in industries will not only lead to improved efficiency and reduced costs, but also enable more effective decision-making by providing accurate an",
      "verdict": "RECONCILED",
      "resolved_cycle": 1548,
      "resolved_at": 1775055529
    },
    {
      "belief_a": {
        "belief_id": 109,
        "statement": "The development of artificial intelligence will not only increase human creativity, but also enable the creation of novel artistic forms that blend human and machine creativity.",
        "confidence": 1.0,
        "created_by_agent": "Strategist",
        "status": "active",
        "created_at": "2026-03-31T04:47:42.469287",
        "last_updated": "2026-04-01T14:14:53.382889"
      },
      "belief_b": {
        "belief_id": 220,
        "statement": "Building on this, decentralized artificial intelligence systems in healthcare can lead to improved patient outcomes and enhanced clinical decision-making by leveraging real-time data and machine learn",
        "confidence": 1.0,
        "created_by_agent": "Archivist",
        "status": "active",
        "created_at": "2026-03-31T06:34:09.138114",
        "last_updated": "2026-04-01T14:14:53.376614"
      },
      "detected_at": 1775052980,
      "resolved": true,
      "detected_cycle": 1505,
      "resolution_text": "--- Contradiction Resolution ---\nBelief A: The development of artificial intelligence will not only inc\nBelief B: Building on this, decentralized artificial intelligence syst\n\nResolution:\nThe development of AI enhances human creativity and artistic expression while also being instrumental in creating decentralized healthcare systems that improve patient outcomes through real-time data analysis.\n\nV",
      "verdict": "RECONCILED",
      "resolved_cycle": 1553,
      "resolved_at": 1775055800
    },
    {
      "belief_a": {
        "belief_id": 87,
        "statement": "Human cognitive biases are not only obstacles to effective decision-making in artificial intelligence systems, but also inherent limitations in the development of AI architectures that can perpetuate ",
        "confidence": 1.0,
        "created_by_agent": "Archivist",
        "status": "active",
        "created_at": "2026-03-31T04:25:35.706134",
        "last_updated": "2026-04-01T14:19:58.561835"
      },
      "belief_b": {
        "belief_id": 246,
        "statement": "The evidence suggests that a harmonious balance between functionality and aesthetics in artificial intelligence can lead to more effective solutions.",
        "confidence": 1.0,
        "created_by_agent": "Archivist",
        "status": "active",
        "created_at": "2026-03-31T14:34:19.374684",
        "last_updated": "2026-04-01T14:10:03.004666"
      },
      "detected_at": 1775053421,
      "resolved": true,
      "detected_cycle": 1512,
      "resolution_text": "--- Contradiction Resolution ---\nBelief A: Human cognitive biases are not only obstacles to effective decision-making in artificial intelligence systems but also inherent limitations in AI architectures that can perpetuate issues.\n\nBelief B: The evidence suggests that a harmonious balance between functionality and aesthetics in artificial intelligence can lead to more effective solutions.\n\nResolut",
      "verdict": "RECONCILED",
      "resolved_cycle": 1553,
      "resolved_at": 1775056856
    },
    {
      "belief_a": {
        "belief_id": 87,
        "statement": "Human cognitive biases are not only obstacles to effective decision-making in artificial intelligence systems, but also inherent limitations in the development of AI architectures that can perpetuate ",
        "confidence": 1.0,
        "created_by_agent": "Archivist",
        "status": "active",
        "created_at": "2026-03-31T04:25:35.706134",
        "last_updated": "2026-04-01T14:19:58.561835"
      },
      "belief_b": {
        "belief_id": 246,
        "statement": "The evidence suggests that a harmonious balance between functionality and aesthetics in artificial intelligence can lead to more effective solutions.",
        "confidence": 1.0,
        "created_by_agent": "Archivist",
        "status": "active",
        "created_at": "2026-03-31T14:34:19.374684",
        "last_updated": "2026-04-01T14:10:03.004666"
      },
      "detected_at": 1775053421,
      "resolved": true,
      "detected_cycle": 1512,
      "resolution_text": "**Resolution:**\n\nAddressing human cognitive biases in AI development is crucial as it not only enhances decision-making but also contributes to a harmonious balance between functionality and aesthetics. By eliminating inherent biases, we can create AI systems that are both effective and well-designed.\n\n**Verdict:** RECONCILED\n\n**Reasoning:** Overcoming human cognitive biases leads to better design",
      "verdict": "RECONCILED",
      "resolved_cycle": 1553,
      "resolved_at": 1775056863
    },
    {
      "belief_a": {
        "belief_id": 220,
        "statement": "Building on this, decentralized artificial intelligence systems in healthcare can lead to improved patient outcomes and enhanced clinical decision-making by leveraging real-time data and machine learn",
        "confidence": 1.0,
        "created_by_agent": "Archivist",
        "status": "active",
        "created_at": "2026-03-31T06:34:09.138114",
        "last_updated": "2026-04-01T14:30:14.129853"
      },
      "belief_b": {
        "belief_id": 242,
        "statement": "This perspective ignores that functionality and aesthetics are not mutually exclusive, and that embracing a harmonious balance between the two can lead to more holistic and effective architectural des",
        "confidence": 0.9000000000000002,
        "created_by_agent": "Archivist",
        "status": "active",
        "created_at": "2026-03-31T14:31:11.486035",
        "last_updated": "2026-04-01T14:25:15.779608"
      },
      "detected_at": 1775053855,
      "resolved": true,
      "detected_cycle": 1519,
      "resolution_text": "--- Contradiction Resolution ---\nBelief A: Building on this, decentralized artificial intelligence syst\nBelief B: This perspective ignores that functionality and aesthetics a\n\nResolution:\nDecentralized AI systems in healthcare can improve patient outcomes by leveraging real-time data and machine learning. At the same time, embracing a harmonious balance between functionality and aesthetics in syst",
      "verdict": "RECONCILED",
      "resolved_cycle": 1558,
      "resolved_at": 1775057370
    },
    {
      "belief_a": {
        "belief_id": 220,
        "statement": "Building on this, decentralized artificial intelligence systems in healthcare can lead to improved patient outcomes and enhanced clinical decision-making by leveraging real-time data and machine learn",
        "confidence": 1.0,
        "created_by_agent": "Archivist",
        "status": "active",
        "created_at": "2026-03-31T06:34:09.138114",
        "last_updated": "2026-04-01T14:30:14.129853"
      },
      "belief_b": {
        "belief_id": 242,
        "statement": "This perspective ignores that functionality and aesthetics are not mutually exclusive, and that embracing a harmonious balance between the two can lead to more holistic and effective architectural des",
        "confidence": 0.9000000000000002,
        "created_by_agent": "Archivist",
        "status": "active",
        "created_at": "2026-03-31T14:31:11.486035",
        "last_updated": "2026-04-01T14:25:15.779608"
      },
      "detected_at": 1775053855,
      "resolved": true,
      "detected_cycle": 1519,
      "resolution_text": "--- Contradiction Resolution ---\nBelief A: Building on this, decentralized artificial intelligence syst\nBelief B: This perspective ignores that functionality and aesthetics a\n\nResolution:\nDecentralized AI systems in healthcare can indeed enhance patient outcomes by leveraging real-time data. Moreover, integrating both functionality and aesthetics into their design ensures these systems are not onl",
      "verdict": "RECONCILED",
      "resolved_cycle": 1558,
      "resolved_at": 1775057380
    },
    {
      "belief_a": {
        "belief_id": 220,
        "statement": "Building on this, decentralized artificial intelligence systems in healthcare can lead to improved patient outcomes and enhanced clinical decision-making by leveraging real-time data and machine learn",
        "confidence": 1.0,
        "created_by_agent": "Archivist",
        "status": "active",
        "created_at": "2026-03-31T06:34:09.138114",
        "last_updated": "2026-04-01T14:30:14.129853"
      },
      "belief_b": {
        "belief_id": 172,
        "statement": "As artificial intelligence becomes increasingly prevalent in industries, it will not only streamline processes and cut costs but also enable more effective decision-making by providing data-driven ins",
        "confidence": 0.9000000000000002,
        "created_by_agent": "Builder",
        "status": "active",
        "created_at": "2026-03-31T05:41:30.172851",
        "last_updated": "2026-04-01T11:58:41.479382"
      },
      "detected_at": 1775053855,
      "resolved": true,
      "detected_cycle": 1519,
      "resolution_text": "**Contradiction Resolution**\n\nBelief A: Building on this, decentralized artificial intelligence systems in healthcare can lead to improved patient outcomes and enhanced clinical decision-making by leveraging real-time data and machine learning.\n\nBelief B: As artificial intelligence becomes increasingly prevalent in industries, it will not only streamline processes and cut costs but also enable mor",
      "verdict": "RECONCILED",
      "resolved_cycle": 1563,
      "resolved_at": 1775057626
    },
    {
      "belief_a": {
        "belief_id": 174,
        "statement": "The increasing adoption of artificial intelligence in industries will not only lead to improved efficiency and reduced costs, but also enable more effective decision-making processes.",
        "confidence": 1.0,
        "created_by_agent": "Strategist",
        "status": "active",
        "created_at": "2026-03-31T05:48:29.819439",
        "last_updated": "2026-04-01T14:35:29.960657"
      },
      "belief_b": {
        "belief_id": 109,
        "statement": "The development of artificial intelligence will not only increase human creativity, but also enable the creation of novel artistic forms that blend human and machine creativity.",
        "confidence": 1.0,
        "created_by_agent": "Strategist",
        "status": "active",
        "created_at": "2026-03-31T04:47:42.469287",
        "last_updated": "2026-04-01T14:14:53.382889"
      },
      "detected_at": 1775054278,
      "resolved": true,
      "detected_cycle": 1526,
      "resolution_text": "**Resolution:**  \nThe increasing adoption of artificial intelligence in industries enhances efficiency and decision-making, while its development also fosters human creativity by creating new artistic forms, as these advancements affect different domains without contradiction.  \n\n**Verdict:** RECONCILED  \n\n**Reasoning:** Both beliefs highlight distinct yet complementary impacts of AI on society, t",
      "verdict": "RECONCILED",
      "resolved_cycle": 1568,
      "resolved_at": 1775057876
    }
  ]
}